dtu_adn/DTU_ADN.py
dtu_adn/__init__.py
dtu_adn/test.py
dtu_adn/data/network_10kV_400V/bus_26.csv
dtu_adn/data/network_10kV_400V/bus_27.csv
dtu_adn/data/network_10kV_400V/bus_28.csv
dtu_adn/data/network_10kV_400V/bus_29.csv
dtu_adn/data/network_10kV_400V/bus_30.csv
dtu_adn/data/network_10kV_400V/bus_31.csv
dtu_adn/data/network_10kV_400V/bus_34.csv
dtu_adn/data/network_10kV_400V/bus_35.csv
dtu_adn/data/network_10kV_400V/bus_37.csv
dtu_adn/data/network_10kV_400V/bus_38.csv
dtu_adn/data/network_10kV_400V/bus_39.csv
dtu_adn/data/network_10kV_400V/bus_42.csv
dtu_adn/data/network_10kV_400V/bus_43.csv
dtu_adn/data/network_10kV_400V/bus_44.csv
dtu_adn/data/network_10kV_400V/bus_45.csv
dtu_adn/data/network_10kV_400V/bus_46.csv
dtu_adn/data/network_10kV_400V/bus_47.csv
dtu_adn/data/network_10kV_400V/gen_26.csv
dtu_adn/data/network_10kV_400V/gen_27.csv
dtu_adn/data/network_10kV_400V/gen_28.csv
dtu_adn/data/network_10kV_400V/gen_29.csv
dtu_adn/data/network_10kV_400V/gen_30.csv
dtu_adn/data/network_10kV_400V/gen_31.csv
dtu_adn/data/network_10kV_400V/gen_34.csv
dtu_adn/data/network_10kV_400V/gen_35.csv
dtu_adn/data/network_10kV_400V/gen_37.csv
dtu_adn/data/network_10kV_400V/gen_38.csv
dtu_adn/data/network_10kV_400V/gen_39.csv
dtu_adn/data/network_10kV_400V/gen_42.csv
dtu_adn/data/network_10kV_400V/gen_43.csv
dtu_adn/data/network_10kV_400V/gen_44.csv
dtu_adn/data/network_10kV_400V/gen_45.csv
dtu_adn/data/network_10kV_400V/gen_46.csv
dtu_adn/data/network_10kV_400V/gen_47.csv
dtu_adn/data/network_10kV_400V/line_26.csv
dtu_adn/data/network_10kV_400V/line_27.csv
dtu_adn/data/network_10kV_400V/line_28.csv
dtu_adn/data/network_10kV_400V/line_29.csv
dtu_adn/data/network_10kV_400V/line_30.csv
dtu_adn/data/network_10kV_400V/line_31.csv
dtu_adn/data/network_10kV_400V/line_34.csv
dtu_adn/data/network_10kV_400V/line_35.csv
dtu_adn/data/network_10kV_400V/line_37.csv
dtu_adn/data/network_10kV_400V/line_38.csv
dtu_adn/data/network_10kV_400V/line_39.csv
dtu_adn/data/network_10kV_400V/line_42.csv
dtu_adn-0.0.1.dist-info/LICENSE
dtu_adn-0.0.1.dist-info/METADATA
dtu_adn-0.0.1.dist-info/WHEEL
dtu_adn-0.0.1.dist-info/top_level.txt
dtu_adn-0.0.1.dist-info/zip-safe
dtu_adn-0.0.1.dist-info/RECORD
